{
  "release_sha": "d026a74e8920a6ae5ca3d3eec90b4dd5069eb62a",
  "governance_lead": "David Harris",
  "governance_lead_approved": true,
  "cab_chair": "Platform CAB Chair",
  "cab_approved": true,
  "uat_report_path": "docs/evidence/RUNNER_SHEET_RELEASE_ROLLOUT_2026-03-24.md",
  "rollback_drill_path": "docs/runbooks/rollback-drills.md",
  "approved_at_utc": "2026-04-04T20:58:18+00:00",
  "deployment_evidence": {
    "ci_run": "https://github.com/cgtqwmwkhp-rgb/quality-governance-platform/actions/runs/23987095001",
    "staging_deploy_run_id": "23987181469",
    "production_deploy_run_id": "23987289410",
    "production_workflow_run_auto_skipped_examples": "23987278220 (freeze — Build and Deploy skipped); 23986237179 (freeze); 23986708127 (freeze); see docs/runbooks/cd-workflow-outcomes.md",
    "production_promotion": "workflow_dispatch staging_verified=true release_sha=45b05775648875c37e927c8301fb8ba1ae5e55bf force_deploy=true (weekend UTC freeze override; promote #420 signoff JSON on main after auto prod run 23987278220 skipped deploy)",
    "production_live_verified_utc": "2026-04-04T20:58:18Z",
    "production_live_build_sha": "45b05775648875c37e927c8301fb8ba1ae5e55bf",
    "production_live_build_time": "2026-04-04T20:58:18Z",
    "production_baseline_build_sha": "7444d1732322a73f36e3583bd787f88539f236e3",
    "production_baseline_observed_utc": "2026-04-04T20:28:36Z",
    "mainline_commits_promoted_first_parent": 2,
    "mainline_promotion_steps": [
      "45b05775648875c37e927c8301fb8ba1ae5e55bf — Merge PR #420 (Predator v4 release_signoff / completion evidence)",
      "7444d1732322a73f36e3583bd787f88539f236e3 — Merge PR #419 (auto-prod descendant gate + runbook)",
      "89cc9818deb9a2f6a39d8d960044ae42fc51d22d — Merge PR #418 (release_signoff evidence refresh for #417)",
      "d026a74e8920a6ae5ca3d3eec90b4dd5069eb62a — Merge PR #417 (xml_import mypy, quarantine messaging, cd-workflow-outcomes.md)"
    ],
    "staging_deploy_head_sha": "45b05775648875c37e927c8301fb8ba1ae5e55bf",
    "staging_last_recorded_deploy_sha_before_promotion": "7444d1732322a73f36e3583bd787f88539f236e3",
    "governance_note": "Signed release_sha stays d026a74e (application merge). Manual promotion used release_sha=45b05775 to match staged main tip (#420). Auto production run 23987278220 succeeded but skipped Build and Deploy due to deploy freeze; force_dispatch cleared freeze. See docs/runbooks/cd-workflow-outcomes.md.",
    "pr_checks_passed": "CI success on main at 45b05775 — run 23987095001",
    "unit_tests": "Per CI run 23987095001",
    "mypy": "Per CI run 23987095001",
    "frontend_tests": "Per CI run 23987095001",
    "coverage_threshold": "Per CI fail_under at merge of PR #420",
    "changes_this_release": [
      "PR #420: release_signoff.json — Predator v4 pipeline evidence (prior cycle)",
      "PR #419: deploy-production.yml — descendant gate; cd-workflow-outcomes.md",
      "PR #418: release_signoff alignment for #417 promotion",
      "PR #417: xml_import, pyproject, quarantine copy, cd-workflow-outcomes.md"
    ],
    "pre_existing_failures": [
      {
        "job": "dast-zap-baseline",
        "reason": "Advisory per docs/compliance/ci-gate-hygiene.md",
        "risk": "none"
      }
    ]
  }
}
